{
  "questions": [
    {
      "question": "什么是“易制毒化学品”？",
      "option": [
        "可用于制造毒品的前体和原料",
        "具有剧毒性危害的化学品",
        "具有易燃、易爆、有毒、有害特性的化学品",
        "可能对人员、设施和环境造成伤害的化学品"
      ],
      "answer": "可用于制造毒品的前体和原料"
    },
    {
      "question": "什么是“危险源”？",
      "option": [
        "事故发生的根源",
        "系统中具有潜在危险能量和物质的区域",
        "能量传出或爆发的地方",
        "事故预防和控制措施"
      ],
      "answer": "事故发生的根源"
    },
    {
      "question": "什么是“化学危险物质”？",
      "option": [
        "可用于制造毒品的前体和原料",
        "具有剧毒性危害的化学品",
        "具有易燃、易爆、有毒、有害特性的化学品",
        "可能对人员、设施和环境造成伤害的化学品"
      ],
      "answer": "具有易燃、易爆、有毒、有害特性的化学品"
    },
    {
      "question": "爆炸品按危险性分为几类？",
      "option": [
        "3类",
        "4类",
        "5类",
        "6类"
      ],
      "answer": "5类"
    },
    {
      "question": "什么是“易制毒化学品”？",
      "option": [
        "可用于制造毒品的前体和原料",
        "具有剧毒性危害的化学品",
        "具有易燃、易爆、有毒、有害特性的化学品",
        "可能对人员、设施和环境造成伤害的化学品"
      ],
      "answer": "可用于制造毒品的前体和原料"
    },
    {
      "question": "什么是“危险源”？",
      "option": [
        "事故发生的根源",
        "系统中具有潜在危险能量和物质的区域",
        "能量传出或爆发的地方",
        "事故预防和控制措施"
      ],
      "answer": "事故发生的根源"
    },
    {
      "question": "什么是“化学危险物质”？",
      "option": [
        "可用于制造毒品的前体和原料",
        "具有剧毒性危害的化学品",
        "具有易燃、易爆、有毒、有害特性的化学品",
        "可能对人员、设施和环境造成伤害的化学品"
      ],
      "answer": "具有易燃、易爆、有毒、有害特性的化学品"
    },
    {
      "question": "爆炸品按危险性分为几类？",
      "option": [
        "3类",
        "4类",
        "5类",
        "6类"
      ],
      "answer": "5类"
    },
    {
      "question": "什么是“易制毒化学品”？",
      "option": [
        "可用于制造毒品的前体和原料",
        "具有剧毒性危害的化学品",
        "具有易燃、易爆、有毒、有害特性的化学品",
        "可能对人员、设施和环境造成伤害的化学品"
      ],
      "answer": "可用于制造毒品的前体和原料"
    },
    {
      "question": "什么是“危险源”？",
      "option": [
        "事故发生的根源",
        "系统中具有潜在危险能量和物质的区域",
        "能量传出或爆发的地方",
        "事故预防和控制措施"
      ],
      "answer": "事故发生的根源"
    },
    {
      "question": "什么是“化学危险物质”？",
      "option": [
        "可用于制造毒品的前体和原料",
        "具有剧毒性危害的化学品",
        "具有易燃、易爆、有毒、有害特性的化学品",
        "可能对人员、设施和环境造成伤害的化学品"
      ],
      "answer": "具有易燃、易爆、有毒、有害特性的化学品"
    },
    {
      "question": "爆炸品按危险性分为几类？",
      "option": [
        "3类",
        "4类",
        "5类",
        "6类"
      ],
      "answer": "5类"
    },
    {
      "question": "金属钠着火时，应怎样做？",
      "option": [
        "用泡沫灭火器灭火",
        "用水灭火",
        "用二氧化碳灭火器灭火",
        "将砂子倒在它上面"
      ],
      "answer": "将砂子倒在它上面"
    },
    {
      "question": "以下哪个不是爆炸品的分类",
      "option": [
        "具有整体爆炸危险的物质和物品",
        "具有抛射危险，但无整体爆炸危险的物质和物品",
        "具有放射性危险的物质和物品",
        "具有燃烧危险和较小爆炸危险或较小抛射危险"
      ],
      "answer": "具有放射性危险的物质和物品"
    },
    {
      "question": "易燃液体是指在可预见的使用条件下能产生易燃蒸气或薄雾，闪点低于多少摄氏度的液体？",
      "option": [
        "45",
        "21",
        "0",
        "-40"
      ],
      "answer": "45"
    },
    {
      "question": "以下哪个类别不同与其他选项？",
      "option": [
        "易燃固体",
        "氧化剂",
        "自燃物品",
        "遇湿易燃物品"
      ],
      "answer": "氧化剂"
    },
    {
      "question": "有机过氧化物系有什么特点",
      "option": [
        "易燃易爆",
        "极易分解",
        "对热、震动或摩擦极为敏感",
        "低温"
      ],
      "answer": "低温"
    },
    {
      "question": "固体有毒品经口摄取半数致死量为多少？",
      "option": [
        "LD50<=500mg/kg",
        "LD50<=200mg/kg",
        "LD50<=1000mg/kg",
        "LD5C50<=10mg/kg"
      ],
      "answer": "LD50<=500mg/kg"
    },
    {
      "question": "液体有毒品经口摄取半数致死量为多少？",
      "option": [
        "LD50<=500mg/kg",
        "LD50<=200mg/kg",
        "LD50<=1000mg/kg",
        "LD5C50<=10mg/kg"
      ],
      "answer": "LD50<=200mg/kg"
    },
    {
      "question": "以下哪个不是腐蚀品的分类？",
      "option": [
        "酸性腐蚀品",
        "碱性腐蚀品",
        "中性腐蚀品",
        "其他腐蚀品"
      ],
      "answer": "中性腐蚀品"
    },
    {
      "question": "金属钠着火时，应怎样做？",
      "option": [
        "用泡沫灭火器灭火",
        "用水灭火",
        "用二氧化碳灭火器灭火",
        "将砂子倒在它上面"
      ],
      "answer": "将砂子倒在它上面"
    },
    {
      "question": "以下哪个不是爆炸品的分类",
      "option": [
        "具有整体爆炸危险的物质和物品",
        "具有抛射危险，但无整体爆炸危险的物质和物品",
        "具有放射性危险的物质和物品",
        "具有燃烧危险和较小爆炸危险或较小抛射危险"
      ],
      "answer": "具有放射性危险的物质和物品"
    },
    {
      "question": "易燃液体是指在可预见的使用条件下能产生易燃蒸气或薄雾，闪点低于多少摄氏度的液体？",
      "option": [
        "45",
        "21",
        "0",
        "-40"
      ],
      "answer": "45"
    },
    {
      "question": "以下哪个类别不同与其他选项？",
      "option": [
        "易燃固体",
        "氧化剂",
        "自燃物品",
        "遇湿易燃物品"
      ],
      "answer": "氧化剂"
    },
    {
      "question": "有机过氧化物系有什么特点",
      "option": [
        "易燃易爆",
        "极易分解",
        "对热、震动或摩擦极为敏感",
        "低温"
      ],
      "answer": "低温"
    },
    {
      "question": "固体有毒品经口摄取半数致死量为多少？",
      "option": [
        "LD50<=500mg/kg",
        "LD50<=200mg/kg",
        "LD50<=1000mg/kg",
        "LD5C50<=10mg/kg"
      ],
      "answer": "LD50<=500mg/kg"
    },
    {
      "question": "液体有毒品经口摄取半数致死量为多少？",
      "option": [
        "LD50<=500mg/kg",
        "LD50<=200mg/kg",
        "LD50<=1000mg/kg",
        "LD5C50<=10mg/kg"
      ],
      "answer": "LD50<=200mg/kg"
    },
    {
      "question": "以下哪个不是腐蚀品的分类？",
      "option": [
        "酸性腐蚀品",
        "碱性腐蚀品",
        "中性腐蚀品",
        "其他腐蚀品"
      ],
      "answer": "中性腐蚀品"
    },
    {
      "question": "金属钠着火时，应怎样做？",
      "option": [
        "用泡沫灭火器灭火",
        "用水灭火",
        "用二氧化碳灭火器灭火",
        "将砂子倒在它上面"
      ],
      "answer": "将砂子倒在它上面"
    },
    {
      "question": "以下哪个不是爆炸品的分类",
      "option": [
        "具有整体爆炸危险的物质和物品",
        "具有抛射危险，但无整体爆炸危险的物质和物品",
        "具有放射性危险的物质和物品",
        "具有燃烧危险和较小爆炸危险或较小抛射危险"
      ],
      "answer": "具有放射性危险的物质和物品"
    },
    {
      "question": "易燃液体是指在可预见的使用条件下能产生易燃蒸气或薄雾，闪点低于多少摄氏度的液体？",
      "option": [
        "45",
        "21",
        "0",
        "-40"
      ],
      "answer": "45"
    },
    {
      "question": "以下哪个类别不同与其他选项？",
      "option": [
        "易燃固体",
        "氧化剂",
        "自燃物品",
        "遇湿易燃物品"
      ],
      "answer": "氧化剂"
    },
    {
      "question": "有机过氧化物系有什么特点",
      "option": [
        "易燃易爆",
        "极易分解",
        "对热、震动或摩擦极为敏感",
        "低温"
      ],
      "answer": "低温"
    },
    {
      "question": "固体有毒品经口摄取半数致死量为多少？",
      "option": [
        "LD50<=500mg/kg",
        "LD50<=200mg/kg",
        "LD50<=1000mg/kg",
        "LD5C50<=10mg/kg"
      ],
      "answer": "LD50<=500mg/kg"
    },
    {
      "question": "液体有毒品经口摄取半数致死量为多少？",
      "option": [
        "LD50<=500mg/kg",
        "LD50<=200mg/kg",
        "LD50<=1000mg/kg",
        "LD5C50<=10mg/kg"
      ],
      "answer": "LD50<=200mg/kg"
    },
    {
      "question": "以下哪个不是腐蚀品的分类？",
      "option": [
        "酸性腐蚀品",
        "碱性腐蚀品",
        "中性腐蚀品",
        "其他腐蚀品"
      ],
      "answer": "中性腐蚀品"
    },
    {
      "question": "金属钠着火时，应怎样做？",
      "option": [
        "用泡沫灭火器灭火",
        "用水灭火",
        "用二氧化碳灭火器灭火",
        "将砂子倒在它上面"
      ],
      "answer": "将砂子倒在它上面"
    },
    {
      "question": "以下哪个不是爆炸品的分类",
      "option": [
        "具有整体爆炸危险的物质和物品",
        "具有抛射危险，但无整体爆炸危险的物质和物品",
        "具有放射性危险的物质和物品",
        "具有燃烧危险和较小爆炸危险或较小抛射危险"
      ],
      "answer": "具有放射性危险的物质和物品"
    },
    {
      "question": "易燃液体是指在可预见的使用条件下能产生易燃蒸气或薄雾，闪点低于多少摄氏度的液体？",
      "option": [
        "45",
        "21",
        "0",
        "-40"
      ],
      "answer": "45"
    },
    {
      "question": "以下哪个类别不同与其他选项？",
      "option": [
        "易燃固体",
        "氧化剂",
        "自燃物品",
        "遇湿易燃物品"
      ],
      "answer": "氧化剂"
    },
    {
      "question": "有机过氧化物系有什么特点",
      "option": [
        "易燃易爆",
        "极易分解",
        "对热、震动或摩擦极为敏感",
        "低温"
      ],
      "answer": "低温"
    },
    {
      "question": "固体有毒品经口摄取半数致死量为多少？",
      "option": [
        "LD50<=500mg/kg",
        "LD50<=200mg/kg",
        "LD50<=1000mg/kg",
        "LD5C50<=10mg/kg"
      ],
      "answer": "LD50<=500mg/kg"
    },
    {
      "question": "液体有毒品经口摄取半数致死量为多少？",
      "option": [
        "LD50<=500mg/kg",
        "LD50<=200mg/kg",
        "LD50<=1000mg/kg",
        "LD5C50<=10mg/kg"
      ],
      "answer": "LD50<=200mg/kg"
    },
    {
      "question": "以下哪个不是腐蚀品的分类？",
      "option": [
        "酸性腐蚀品",
        "碱性腐蚀品",
        "中性腐蚀品",
        "其他腐蚀品"
      ],
      "answer": "中性腐蚀品"
    }
  ]
}


